LICENSE
MANIFEST.in
README.md
setup.py
tencentyun_porndetect/__init__.py
tencentyun_porndetect/porndetect.py
tencentyun_porndetect.egg-info/PKG-INFO
tencentyun_porndetect.egg-info/SOURCES.txt
tencentyun_porndetect.egg-info/dependency_links.txt
tencentyun_porndetect.egg-info/requires.txt
tencentyun_porndetect.egg-info/top_level.txt