Metadata-Version: 1.0
Name: tencentyun-porndetect
Version: 1.0.0
Summary: TencentYun Porndetect for Python SDK
Home-page: https://github.com/newliver/tencentyun-prondetect
Author: newliver
Author-email: updatanow@gmail.com
License: MIT
Keywords: tencentyun,porndetect
Platform: UNKNOWN
